tbas/__init__.py
tbas/badge_io.py
tbas/buffer.py
tbas/corpus.py
tbas/datatypes.py
tbas/interpreter.py
tbas/machine.py
tbas/ui.py
tbas/util.py
tbas/gui/__init__.py
tbas/gui/cell.py
tbas/gui/memory.py
tbas/gui/program.py
tbas/gui/status.py
tbas/gui/toolbar.py
tests/__init__.py
tests/tests.py
tbas_py-0.1.1.dist-info/LICENSE
tbas_py-0.1.1.dist-info/METADATA
tbas_py-0.1.1.dist-info/WHEEL
tbas_py-0.1.1.dist-info/entry_points.txt
tbas_py-0.1.1.dist-info/top_level.txt
tbas_py-0.1.1.dist-info/RECORD
