Metadata-Version: 2.1
Name: tbas-py
Version: 0.1.1
Summary: Python interpreter for Tis But A Scratch (Brainfuck derivative)
Home-page: https://github.com/ehennenfent/tbas_python
Author: Eric Hennenfent
Author-email: ecapstone@gmail.com
License: UNKNOWN
Keywords: tbas
Platform: UNKNOWN
